chamber_backup_diff/__init__.py
chamber_backup_diff/cli.py
chamber_backup_diff/diff.py
chamber_backup_diff/exception_handler.py
chamber_backup_diff/shell.py
chamber_backup_diff/version.py
chamber_backup_diff-0.1.3.dist-info/entry_points.txt
chamber_backup_diff-0.1.3.dist-info/LICENSE
chamber_backup_diff-0.1.3.dist-info/WHEEL
chamber_backup_diff-0.1.3.dist-info/METADATA
chamber_backup_diff-0.1.3.dist-info/RECORD
